kronos/_version.py
kronos/application.py
kronos/channel.py
kronos/flags.py
kronos/ioc.py
kronos/main.py
dg645_ioc-0.5.13.dist-info/LICENSE
dg645_ioc-0.5.13.dist-info/METADATA
dg645_ioc-0.5.13.dist-info/WHEEL
dg645_ioc-0.5.13.dist-info/entry_points.txt
dg645_ioc-0.5.13.dist-info/top_level.txt
dg645_ioc-0.5.13.dist-info/RECORD
