Metadata-Version: 2.1
Name: dg645-ioc
Version: 0.5.13
Summary: CAproto-based pure-Python EPICS IOC for the Stanford Research Systems DG645 delay generator.
Author-email: Matthias Rössle <matthias.roessle@helmholtz-berlin.de>, Florin Boariu <florin.pt@rootshell.ro>
Project-URL: Source, https://gitlab.com/kmc3-xpp/kronos-ioc
Project-URL: Issues, https://gitlab.com/kmc3-xpp/kronos-ioc/-/issues
Classifier: Programming Language :: Python :: 3
Classifier: License :: OSI Approved :: GNU General Public License v3 or later (GPLv3+)
Classifier: Operating System :: POSIX :: Linux
Classifier: Development Status :: 2 - Pre-Alpha
Classifier: Environment :: Console
Classifier: Intended Audience :: Science/Research
Classifier: Topic :: Scientific/Engineering
Requires-Python: >=3.8
License-File: LICENSE
Requires-Dist: caproto
Requires-Dist: emmi >=0.5.0
Requires-Dist: pyvisa-py
Requires-Dist: pyvisa-sim
Requires-Dist: parse
Provides-Extra: test
Requires-Dist: pytest ; extra == 'test'
Requires-Dist: pytest-cov ; extra == 'test'
Requires-Dist: pytest-asyncio ; extra == 'test'
